MANIFEST.in
setup.cfg
setup.py
cbktree.egg-info/PKG-INFO
cbktree.egg-info/SOURCES.txt
cbktree.egg-info/dependency_links.txt
cbktree.egg-info/requires.txt
cbktree.egg-info/top_level.txt
lib/__init__.py
lib/bktree.hpp
lib/cyHamDb.cpp
lib/cyHamDb.pyx
lib/version.py
test/test_bktree.py
test/test_bktree_2.py