Metadata-Version: 1.0
Name: cbktree
Version: 0.3.1
Summary: bktree data structure
Home-page: https://github.com/gpip/cBKTree
Author: Guilherme Polo
Author-email: UNKNOWN
License: UNKNOWN
Platform: UNKNOWN
